MANIFEST.in
setup.py
cinemasci/__init__.py
cinemasci.egg-info/PKG-INFO
cinemasci.egg-info/SOURCES.txt
cinemasci.egg-info/dependency_links.txt
cinemasci.egg-info/requires.txt
cinemasci.egg-info/top_level.txt
cinemasci/cdb/__init__.py
cinemasci/cis/__init__.py
cinemasci/cis/channel.py
cinemasci/cis/cisview.py
cinemasci/cis/colormap.py
cinemasci/cis/imageview.py
cinemasci/cis/layer.py
cinemasci/cis/renderer.py
cinemasci/install/__init__.py
cinemasci/install/__main__.py
cinemasci/pynb/__init__.py
cinemasci/server/__init__.py
cinemasci/server/__main__.py
cinemasci/server/cinema_test.html
cinemasci/server/error_no-database.html
cinemasci/viewers/__init__.py
cinemasci/viewers/cinema_explorer.html
cinemasci/viewers/cinema_simple.html
cinemasci/viewers/cinema_view.html
cinemasci/viewers/cinema/explorer/2.2/databases.json
cinemasci/viewers/cinema/explorer/2.2/css/viewer.css
cinemasci/viewers/cinema/explorer/2.2/js/main.js
cinemasci/viewers/cinema/lib/CinemaComponents.v2.7.1.min.css
cinemasci/viewers/cinema/lib/CinemaComponents.v2.7.1.min.js
cinemasci/viewers/cinema/lib/cinemacomponents.license.md
cinemasci/viewers/cinema/lib/d3.license.md
cinemasci/viewers/cinema/lib/d3.v4.min.js
cinemasci/viewers/cinema/lib/d3.v5.min.js
cinemasci/viewers/cinema/lib/2.2/common.css
cinemasci/viewers/cinema/lib/2.2/databases.js
cinemasci/viewers/cinema/lib/2.2/img/cinema_logo_filmreel_named_100px_white.png
cinemasci/viewers/cinema/lib/2.2/img/empty.png
cinemasci/viewers/cinema/simple/2.2/css/compare.css
cinemasci/viewers/cinema/view/2.2/cinema_attributes_example.json
cinemasci/viewers/cinema/view/2.2/copyright.md
cinemasci/viewers/cinema/view/2.2/databases.json
cinemasci/viewers/cinema/view/2.2/license.md
cinemasci/viewers/cinema/view/2.2/main.js
cinemasci/viewers/cinema/view/2.2/css/range-css.css
cinemasci/viewers/cinema/view/2.2/css/range-css.textClipping
cinemasci/viewers/cinema/view/2.2/css/select-css.css
doc/description.md
scripts/cinema
scripts/cisconvert