Metadata-Version: 2.1
Name: cinemasci
Version: 1.7.7
Summary: Cinema scientific toolset.
Home-page: https://github.com/cinemascience
Author: David H. Rogers
Author-email: dhr@lanl.gov
License: UNKNOWN
Platform: UNKNOWN
Classifier: Programming Language :: Python :: 3
Classifier: License :: OSI Approved :: BSD License
Classifier: Operating System :: OS Independent
